server.py
src/__init__.py
src/document_processor.py
src/prompts.py
src/resource_manager.py
src/translator.py
bookbridge_mcp-1.0.2.dist-info/entry_points.txt
bookbridge_mcp-1.0.2.dist-info/METADATA
bookbridge_mcp-1.0.2.dist-info/WHEEL
bookbridge_mcp-1.0.2.dist-info/RECORD
