Metadata-Version: 2.3
Name: bookbridge-mcp
Version: 1.0.2
Summary: A powerful Model Context Protocol (MCP) server for Chinese-to-English book translation and document processing
License: MIT
Keywords: mcp,translation,document-processing,chinese-english,fastmcp
Author: Polly2014
Author-email: your.email@example.com
Requires-Python: >=3.10,<4.0
Classifier: Development Status :: 4 - Beta
Classifier: Intended Audience :: Developers
Classifier: License :: OSI Approved :: MIT License
Classifier: Programming Language :: Python :: 3
Classifier: Programming Language :: Python :: 3.10
Classifier: Programming Language :: Python :: 3.11
Classifier: Programming Language :: Python :: 3.12
Classifier: Programming Language :: Python :: 3.13
Classifier: Topic :: Software Development :: Libraries :: Python Modules
Classifier: Topic :: Text Processing :: Linguistic
Requires-Dist: aiofiles (>=23.0.0)
Requires-Dist: beautifulsoup4 (>=4.12.0)
Requires-Dist: fastmcp (>=2.0.0)
Requires-Dist: markdown (>=3.5.0)
Requires-Dist: pydantic (>=2.5.0)
Requires-Dist: python-docx (>=1.1.0)
Requires-Dist: python-dotenv (>=1.0.0)
Project-URL: Documentation, https://github.com/Polly2014/BookBridge-MCP-Server#readme
Project-URL: Homepage, https://github.com/Polly2014/BookBridge-MCP-Server
Project-URL: Repository, https://github.com/Polly2014/BookBridge-MCP-Server
